prettierjson/__init__.py
prettierjson/__main__.py
prettierjson/prettierjson.py
prettierjson-1.0.1.dist-info/entry_points.txt
prettierjson-1.0.1.dist-info/WHEEL
prettierjson-1.0.1.dist-info/METADATA
prettierjson-1.0.1.dist-info/RECORD
