Metadata-Version: 2.1
Name: prettierjson
Version: 1.0.1
Summary: Generate prettier and more compact JSON dumps
Home-page: https://github.com/brianburwell11/prettierjson
Author: Brian Burwell
Author-email: brianburwell11@gmail.com
Requires-Python: >=3.9,<4.0
Classifier: Programming Language :: Python :: 3
Classifier: Programming Language :: Python :: 3.10
Classifier: Programming Language :: Python :: 3.9
Project-URL: Documentation, https://github.com/brianburwell11/prettierjson/wiki
Project-URL: Repository, https://github.com/brianburwell11/prettierjson
